kiteapi/.__init__.py.swp
kiteapi/.__init__.py.un~
kiteapi/__init__.py
kiteapi-0.0.1.dist-info/WHEEL
kiteapi-0.0.1.dist-info/METADATA
kiteapi-0.0.1.dist-info/RECORD
