Metadata-Version: 1.2
Name: kiteapi
Version: 0.0.1
Summary: Unofficial Python Api to communicate with your Kite (https://kite.com).
Home-page: https://github.com/Carreau/kiteapi
License: UNKNOWN
Author: Matthias Bussonnier
Author-email: bussonniermatthias@gmail.com
Classifier: License :: OSI Approved :: MIT License
